{
    "cms_forwarder_ver_API": "http://csc1-linux:30083/ForwarderTable/weblogic_12c.json",
    "allClusers" : [
        {
            "cluster": "HKEC",
            "hospList" : [
                "CHC",
                "PYN",
                "RH",
                "SJH",
                "TWE",
                "WCH"
            ]
        },
        {
            "cluster": "HKWC",
            "hospList" : [
                "DKC",
                "FYK",
                "GH",
                "ML",
                "QMH",
                "TWH",
                "TYH"
            ]
        },
        {
            "cluster": "KEC",
            "hospList" : [
                "HHH",
                "TKO",
                "UCH"
            ]
        },
        {
            "cluster": "KCC",
            "hospList" : [
                "BH",
                "HCH",
                "HKE",
                "KH",
                "KWH",
                "OLM",
                "QEH",
                "WTS"
            ]
        },
        {
            "cluster": "KWC",
            "hospList" : [
                "KCH",
                "CMC",
                "NLT",
                "PMH",
                "YCH"
            ]
        },
        {
            "cluster": "NTEC",
            "hospList" : [
                "AHN",
                "BBH",
                "CHS",
                "NDH",
                "PWH",
                "SH",
                "TPH"
            ]
        },
        {
            "cluster": "NTWC",
            "hospList" : [
                "CPH",
                "POH",
                "SLH",
                "TMH",
                "TSH"
            ]
        }
    ]
}